kineticglue/__init__.py
kineticglue-0.0.5.dist-info/METADATA
kineticglue-0.0.5.dist-info/WHEEL
kineticglue-0.0.5.dist-info/top_level.txt
kineticglue-0.0.5.dist-info/RECORD
